chainer_jsonl_report/__init__.py
chainer_jsonl_report/jsonl_reporter.py
chainer_jsonl_report/latest_log.py
chainer_jsonl_report/test_jsonl_report.py
chainer_jsonl_report/test_latest_log.py
chainer_jsonl_report-0.0.5.dist-info/LICENSE
chainer_jsonl_report-0.0.5.dist-info/METADATA
chainer_jsonl_report-0.0.5.dist-info/WHEEL
chainer_jsonl_report-0.0.5.dist-info/top_level.txt
chainer_jsonl_report-0.0.5.dist-info/RECORD
