Metadata-Version: 2.1
Name: chainer-jsonl-report
Version: 0.0.5
Summary: JSONL formatted LogReport extention for chainer.
Home-page: https://github.com/nel215/chainer-jsonl-reporter
Author: nel215
Author-email: otomo.yuhei@gmail.com
License: UNKNOWN
Keywords: machine learning
Platform: UNKNOWN
Requires-Dist: chainer
